setup.py
decolib/__init__.py
decolib.egg-info/PKG-INFO
decolib.egg-info/SOURCES.txt
decolib.egg-info/dependency_links.txt
decolib.egg-info/top_level.txt