Metadata-Version: 1.0
Name: decolib
Version: 0.0.1
Summary: Various python decorators
Home-page: http://bitbucket.org/zeus/decolib
Author: Pavel Zhukov
Author-email: gelios@gmail.com
License: GPL
Keywords: decorators
Platform: UNKNOWN
